lfpykit/__init__.py
lfpykit/cellgeometry.py
lfpykit/eegmegcalc.py
lfpykit/lfpcalc.py
lfpykit/models.py
lfpykit/version.py
lfpykit/tests/fem_mix_dip.npz
lfpykit/tests/test_eegmegcalc.py
lfpykit/tests/test_lfpcalc.py
lfpykit/tests/test_module.py
LFPykit-0.5.1.dist-info/LICENSE
LFPykit-0.5.1.dist-info/METADATA
LFPykit-0.5.1.dist-info/WHEEL
LFPykit-0.5.1.dist-info/top_level.txt
LFPykit-0.5.1.dist-info/RECORD
