Metadata-Version: 2.1
Name: LFPykit
Version: 0.5.1
Summary: Electrostatic models for multicompartment neuron models
Home-page: https://github.com/LFPy/LFPykit
Author: LFPy-team
Author-email: lfpy@users.noreply.github.com
Classifier: Programming Language :: Python :: 3
Classifier: Programming Language :: Python :: 3.7
Classifier: Programming Language :: Python :: 3.8
Classifier: Programming Language :: Python :: 3.9
Classifier: Programming Language :: Python :: 3.10
Classifier: Programming Language :: Python :: 3.11
Classifier: License :: OSI Approved :: GNU General Public License (GPL)
Classifier: Operating System :: OS Independent
Classifier: Topic :: Scientific/Engineering
Classifier: Topic :: Scientific/Engineering :: Physics
Classifier: Topic :: Utilities
Classifier: Intended Audience :: Developers
Classifier: Intended Audience :: Science/Research
Classifier: Development Status :: 4 - Beta
Provides: lfpykit
Requires-Python: >=3.7
Provides-Extra: tests
Provides-Extra: docs
License-File: LICENSE
